<?xml version="1.0" encoding="UTF-8"?>
  <?xml-stylesheet type="text/xsl" href="rfc2629.xslt" ?>
  <!-- generated by https://github.com/cabo/kramdown-rfc2629 version 1.2.8 -->

<!DOCTYPE rfc SYSTEM "rfc2629.dtd" [
]>

<?rfc toc="yes"?>
<?rfc sortrefs="yes"?>
<?rfc symrefs="yes"?>

<rfc ipr="trust200902" docName="draft-soilandreyes-arcp-03" category="info">

  <front>
    <title abbrev="arcp">The Archive and Package (arcp) URI scheme</title>

    <author initials="S." surname="Soiland-Reyes" fullname="Stian Soiland-Reyes">
      <organization>The University of Manchester</organization>
      <address>
        <postal>
          <street>Oxford Road</street>
          <city>Manchester</city>
          <country>United Kingdom</country>
        </postal>
        <email>stain@apache.org</email>
        <uri>http://orcid.org/0000-0001-9842-9718</uri>
      </address>
    </author>
    <author initials="M." surname="Cáceres" fullname="Marcos Cáceres">
      <organization>Mozilla Corporation</organization>
      <address>
        <email>marcos@marcosc.com</email>
        <uri>http://marcosc.com/</uri>
      </address>
    </author>

    <date year="2018" month="February" day="05"/>

    <area>General</area>
    
    <keyword>Internet-Draft</keyword>

    <abstract>


<t>This specification define the
Archive and Package URI scheme <spanx style="verb">arcp</spanx>.</t>

<t>arcp URIs can be used to consume or reference hypermedia
resources bundled inside a file archive or an
application package, as well as to resolve URIs for
archive resources within a programmatic framework.</t>

<t>This URI scheme provides mechanisms to generate a
unique base URI to represent the root of the archive,
so that relative URI references in a bundled resource
can be resolved within the archive without having to
extract the archive content on the local file system.</t>

<t>An arcp URI can be used for purposes of isolation
(e.g. when consuming multiple archives),
security constraints (avoiding “climb out” from the archive),
or for externally identiyfing sub-resources
referenced by hypermedia formats.</t>



    </abstract>


  </front>

  <middle>


<section anchor="introduction" title="Introduction">

<t>Mobile and Web Applications
may bundle resources such as stylesheets with
<spanx style="emph">relative URI references</spanx> <xref target="RFC3986"/> 
(<eref target="https://tools.ietf.org/html/rfc3986#section-4.2">4.2</eref>)
to scripts, images and fonts. Resolving
and parsing
such resources within URI handling frameworks may require
generating absolute URIs and applying
Same-Origin <xref target="RFC6454"/> security policies separately for
each app.</t>

<t>Software that is accessing resources bundled inside an
archive (e.g. <spanx style="verb">zip</spanx> or <spanx style="verb">tar.gz</spanx> file) can struggle to consume
hypermedia content types that use relative
URI references such as <spanx style="verb">../css/</spanx>,
as it is challenging to establishing the <spanx style="emph">base URI</spanx>
<xref target="RFC3986"/> 
(<eref target="https://tools.ietf.org/html/rfc3986#section-5.1">5.1</eref>)
in a consistent fashion.</t>

<t>Frequently the archive might be unpacked locally,
implying base URIs like <spanx style="verb">file:///tmp/a1b27ae03865/</spanx>
to represent the root of the archive. Such URIs are temporary,
might not be globally unique, and could be vulnerable to
attacks such as “climbing out” of the root directory.</t>

<t>An archive containing multiple HTML or
Linked Data resources, such as in a
BagIt archive <xref target="I-D.draft-kunze-bagit-14"/>, may be using
relative URIs to cross-reference constituent files,
making it challenging to index or annotate such resources.</t>

<t>Consumption of an archive with a consistent base URL
should be possible no matter from which location it was retrieved,
on which device it is inspected, and with which 
mechanism the archive is accessed (e.g. virtual file system).</t>

<t>When consuming multiple archives from untrusted sources
it would be beneficial to have a Same Origin policy <xref target="RFC6454"/>
so that relative hyperlinks can’t escape the particular archive.</t>

<t>The <spanx style="verb">file:</spanx> URI scheme <xref target="RFC8089"/>
can be ill-suited for purposes such as above, while a
location-independent URI scheme can be more flexible,
secure and globally unique.</t>

<t>This specification define the 
Archive and Package URI scheme <spanx style="verb">arcp</spanx> as 
an alternative to addressing resources 
within an archive, application or package.</t>

<t>For the purpose of this specification, an <spanx style="strong">archive</spanx> is a
collection of sub-resources addressable by name or path.
This definition covers typical archive file formats like
<spanx style="verb">.zip</spanx> or <spanx style="verb">tar.gz</spanx> and derived <spanx style="verb">+zip</spanx> media types <xref target="RFC6839"/>,
but also non-file resource packages like
an LDP Container <xref target="W3C.REC-ldp-20150226"/>,
an installed Web App <xref target="W3C.WD-appmanifest-20180118"/>,
or a BagIt folder structure <xref target="I-D.draft-kunze-bagit-14"/>.</t>

<t>For brevity, the term <spanx style="emph">archive</spanx> is used throughout this
specification, although from the above it can also mean
a <spanx style="emph">container</spanx>, <spanx style="emph">application</spanx>, <spanx style="emph">aggregation</spanx> or <spanx style="emph">package</spanx>.</t>

<t>The main purpose of arcp URIs is to provide consistent identifiers as absolute
URIs for nested resources. This specification does not define a new network
protocol, however it suggests an abstract resolution protocol that
implementations can apply using existing protocols or 
programming frameworks.</t>

</section>
<section anchor="requirements" title="Requirements Language">

<t>The key words “MUST”, “MUST NOT”, “REQUIRED”, “SHALL”, “SHALL
NOT”, “SHOULD”, “SHOULD NOT”, “RECOMMENDED”,  “MAY”, and
“OPTIONAL” in this document are to be interpreted as described in
<xref target="RFC2119"/>.</t>

</section>
<section anchor="syntax" title="Scheme syntax">

<t>The <spanx style="verb">arcp</spanx> URI scheme follows the <xref target="RFC3986"/> syntax for hierarchical
URIs according to the following productions:</t>

<figure><artwork><![CDATA[
arcp-URI       = arcp-scheme ":" arcp-specific [ "#" fragment ]

arcp-scheme    = "arcp"

arcp-specific  = "//" arcp-authority [ path-absolute ] [ "?" query ]
]]></artwork></figure>

<t>The <spanx style="verb">arcp-authority</spanx> component provides a unique identifier for the opened archive. See <xref target="authority"></xref> for details.</t>

<t>The <spanx style="verb">path-absolute</spanx> component provides the absolute path of a resource
(e.g. a file or directory) within the archive. See <xref target="path"></xref>
for details.</t>

<t>The <spanx style="verb">query</spanx> component MAY be used, but its semantics is undefined by this specification.</t>

<t>The “fragment” component MAY be used by implementations according
to <xref target="RFC3986"/> and the implied media type <xref target="RFC2046"/> of the
resource at the path. This specification does not specify how
to determine the media type.</t>

<section anchor="authority" title="Authority">

<t>The purpose of the <spanx style="verb">authority</spanx> component in an arcp URI is
to build a unique identifier for a particular archive. The
authority is NOT intended to be resolvable without former
knowledge of the archive.</t>

<t>The authority of an arcp URI MUST be valid according to
these productions:</t>

<figure><artwork><![CDATA[
arcp-authority = uuid | ni | name | authority
uuid          = "uuid," UUID
ni            = "ni," alg-val
name          = "name," reg-name
]]></artwork></figure>

<t><list style="numbers">
  <t>The prefix <spanx style="verb">uuid,</spanx> combines with the <spanx style="verb">UUID</spanx> production as defined in <xref target="RFC4122"/>, e.g.
<spanx style="verb">uuid,2a47c495-ac70-4ed1-850b-8800a57618cf</spanx></t>
  <t>The prefix <spanx style="verb">ni,</spanx> combines with the <spanx style="verb">alg-val</spanx> production as defined in <xref target="RFC6920"/>, e.g.
<spanx style="verb">ni,sha-256;JCS7yveugE3UaZiHCs1XpRVfSHaewxAKka0o5q2osg8</spanx></t>
  <t>The prefix <spanx style="verb">name,</spanx> combines with the <spanx style="verb">reg-name</spanx> production
as defined in <xref target="RFC3986"/>, e.g. <spanx style="verb">name,app.example.com</spanx>. For arcp 
IRIs <xref target="RFC3987"/>, its <spanx style="verb">ireg-name</spanx> production applies instead of <spanx style="verb">reg-name</spanx>.</t>
  <t>The production <spanx style="verb">authority</spanx> matches its definition in <xref target="RFC3986"/>, or
<spanx style="verb">iauthority</spanx> for arcp IRIs <xref target="RFC3987"/>. As this necessarily also match 
the above prefixed productions, those should be considered first before 
falling back to this production.</t>
</list></t>

</section>
<section anchor="path" title="Path">

<t>The <spanx style="verb">path-absolute</spanx> component, if present,
MUST match the production in <xref target="RFC3986"/>, 
or <spanx style="verb">ipath-absolute</spanx> for arcp IRIs <xref target="RFC3987"/>. This provide
the absolute path of a resource
(e.g. a file or directory) within the archive.</t>

<t>Archive media types vary in constraints and possibilities on
how to express paths, however implementations SHOULD use <spanx style="verb">/</spanx> as
path separator for nested folders and files.</t>

<t>It is RECOMMENDED to include the trailing <spanx style="verb">/</spanx> if it is known
that the path represents a directory.</t>

</section>
</section>
<section anchor="semantics" title="Scheme semantics">

<t>This specification does not constrain what format
might constitute an <spanx style="emph">archive</spanx>, and neither does it require
that the archive is retrievable as a single bytestream or file.</t>

<t>Examples of retrievable archive media types include
<spanx style="verb">application/zip</spanx>, <spanx style="verb">application/vnd.android.package-archive</spanx>,
<spanx style="verb">application/x-tar</spanx>, <spanx style="verb">application/x-gtar</spanx> and
<spanx style="verb">application/x-7z-compressed</spanx>.</t>

<t>Examples of non-file archives include
an LDP Container <xref target="W3C.REC-ldp-20150226"/>,
an installed Web App <xref target="W3C.WD-appmanifest-20180118"/>,
or a BagIt folder structure <xref target="I-D.draft-kunze-bagit-14"/>.</t>

<section anchor="authority-semantics" title="Authority semantics">

<t>The <spanx style="emph">authority</spanx> component identifies the archive itself.</t>

<t>Implementations MAY assume that two arcp URIs with the
same authority component relate to resources within the same
archive, subject to limitations explained in this section.</t>

<t>The authority prefix, if present, helps to inform consumers
what uniqueness constraints have been used when identifying
the archive, without necessarily providing access to the archive.</t>

<t><list style="numbers">
  <t>If the prefix is <spanx style="verb">uuid,</spanx> followed by a UUID <xref target="RFC4122"/>,
  this indicates a unique archive identity. Applications MAY 
  assume that the corresponding <spanx style="verb">urn:uuid:</spanx> URI 
  identifies the archive.</t>
  <t>If the prefix is <spanx style="verb">uuid,</spanx> followed by a v4 UUID <xref target="RFC4122"/>
  (<eref target="https://tools.ietf.org/html/rfc4122#section-4.4">4.4</eref>),
  this indicate uniqueness based on a random number generator.<vspace />
  Implementations creating random-based
  authorities SHOULD generate the v4 random UUID using
  a suitable random number generator <xref target="RFC4086"/>.</t>
  <t>If the prefix is <spanx style="verb">uuid,</spanx> followed by a v5 name-based UUID <xref target="RFC4122"/>
  (<eref target="https://tools.ietf.org/html/rfc4122#section-4.3">4.3</eref>),
  this indicates uniqueness based on an existing archive location,
  typically an URL.<vspace />
  Implementations creating location-based
  authorities SHOULD generate the
  v5 UUID using the URL
  namespace <spanx style="verb">6ba7b811-9dad-11d1-80b4-00c04fd430c8</spanx>
  and an retrievable archive URL.
  Note that while implementations cannot resolve which location was
  used, they can confirm the name-based UUID if the location
  is otherwise known.</t>
  <t>If the prefix is <spanx style="verb">ni,</spanx> this indicates a unique archive identity
  based on a hashing of the archive’s bytestream or content.
  Implementations MAY assume that resources within an
  <spanx style="verb">ni</spanx> arcp URIs remains static, although the implementation may
  use content negotiation or similar transformations.<vspace />
  The checksum MUST be expressed
  according to the <spanx style="verb">alg-val</spanx> production in <xref target="RFC6920"/> 
  (<eref target="https://tools.ietf.org/search/rfc6920#section-3">3</eref>).
  Implementations creating hash-based authorities from an archive’s
  bytestream SHOULD use the hash method <spanx style="verb">sha-256</spanx> without truncation.
  Implementations MAY assume that the corresponding <spanx style="verb">ni:</spanx> URI
  identifies the archive.</t>
  <t>If the prefix is <spanx style="verb">name,</spanx> this indicates that the authority
  is an application or package name, typically as installed
  on a device or system.<vspace />
  Implementations SHOULD assume that an unrecognised <spanx style="verb">name</spanx>
  authority is only unique within a particular installation,
  but MAY assume further uniqueness guarantees for names under
  their control.<vspace />
  It is RECOMMENDED that implementations creating
  name-based authorities use DNS names under their control,
  for instance an app installed as <spanx style="verb">app.example.com</spanx> can
  make an authority <spanx style="verb">name,app.example.com</spanx> to refer to its
  packaged resources, or <spanx style="verb">name,foo.app.example.com</spanx> to refer to
  its dynamic container of <spanx style="verb">foo</spanx> resources.</t>
</list></t>

<t>The uniqueness properties are <spanx style="strong">unspecified</spanx> for arcp
URIs which authority do not match any of the prefixes defined in
this specification.</t>

</section>
<section anchor="path-semantics" title="Path semantics">

<t>The <spanx style="emph">path</spanx> component of an arcp URI identify individual
resources within a particular archive, typically
a <spanx style="emph">directory</spanx> or <spanx style="emph">file</spanx>.</t>

<t><list style="symbols">
  <t>If the <spanx style="emph">path</spanx> is <spanx style="verb">/</spanx> - e.g. &lt;arcp://uuid,833ebda2-f9a8-4462-b74a-4fcdc1a02d22/&gt; -
then the arcp URI represent the archive itself,
typically represented as a root directory or collection.</t>
  <t>If the path ends with <spanx style="verb">/</spanx> then the path represents
a directory or collection.</t>
</list></t>

<t>The arcp URIs can be used for uniquely identifying
resources within an archive, such as in
an information system considering multiple archives.</t>

<t>Assuming an appropriate mechanism which have
knowledge of the corresponding archive, an arcp URI
can also be used for resolution.</t>

<t>Some archive formats might permit resources
with the same (duplicate) path, in which case it is undefined from
this specification which particular entry is described.</t>

</section>
<section anchor="resolution" title="Resolution protocol">

<t>This specification do not define a network protocol to
resolve resources according to the arcp URI scheme.
For instance, one implementation might rewrite arcp URIs to
localized paths in a temporary directory, while
another implementation might use an embedded HTTP server.</t>

<t>It is envisioned that an implementation will
have accessed an archive in advance, and assigned it an 
appropriate authority according
to <xref target="authority"></xref>. Such an implementation
can then resolve arcp URIs, e.g. by using
in-memory archive access or mapping arcp paths to the
the local file system.</t>

<t>Implementations that support resolving arcp URIs SHOULD:</t>

<t><list style="numbers">
  <t>Fail with the equivalent of <spanx style="emph">Not Found</spanx> if the authority is unknown.</t>
  <t>Fail with the equivalent of <spanx style="emph">Gone</spanx> if the authority is known, but the content of the archive is no longer available.</t>
  <t>Fail with the equivalent of <spanx style="emph">Not Found</spanx> if the path does not map to a resource within the archive.</t>
  <t>Return the corresponding (potentially uncompressed) bytestream if the path maps to a file within the archive.</t>
  <t>Return an appropriate directory listing if the path maps to a directory within the archive.</t>
  <t>Return an appropriate directory listing of the archive’s root directory if the path is <spanx style="verb">/</spanx>.</t>
</list></t>

<t>Implementations MAY support other ways to resolve arcp URIs, e.g.
query parameters or content negotiation.</t>

<t>Not all archive formats or implementations will have the
concept of a directory listing, in which case
the implementation MAY fail such resolutions with the
equivalent of “Not Implemented”.</t>

<t>It is not undefined by this specification how an implementation
can determine the media type of a file within an archive. 
This could be expressed in secondary resources (such as a manifest),
be determined by file extensions or magic bytes.</t>

<t>The media type <spanx style="verb">text/uri-list</spanx> <xref target="RFC2483"/> MAY be used to represent
a directory listing, in which case it SHOULD contain only URIs
with the arcp URI of the directory as a common base.</t>

<t>Some archive formats might support resources which are
neither directories nor regular files (e.g. device files,
symbolic links). This specification does not define the
semantics of attempting to resolve such resources.</t>

<t>This specification does not define how to change an archive
or its content using arcp URIs.</t>

</section>
<section anchor="well-known" title="Resolving from a .well-known endpoint">

<t>If the <spanx style="verb">authority</spanx> component of an arcp URI matches the <spanx style="verb">alg-val</spanx>
production, an application MAY assume corresponding 
<spanx style="verb">ni:///</spanx> or <spanx style="verb">nih:</spanx> URIs <xref target="RFC6920"/> identify the archive 
bytestream or content.</t>

<t>Applications MAY attempt to retrieve the corresponding 
archive from any <spanx style="verb">.well-known/ni/</spanx> endpoint <xref target="RFC5785"/> 
as specified in <xref target="RFC6920"/> 
(<eref target="https://tools.ietf.org/html/rfc6920#section-4">4</eref>).
Applications SHOULD verify the checksum of the
retrieved archive before resolving individual arcp paths.</t>

</section>
</section>
<section anchor="encoding" title="Encoding considerations">

<t>The productions for <spanx style="verb">uuid</spanx> and <spanx style="verb">ni</spanx> are restricted to
URI safe ASCII and should not require any 
encoding considerations.</t>

<t>When arcp is used in IRIs <xref target="RFC3987"/>, the <spanx style="verb">name</spanx> production 
permit Unicode characters corresponding to its <spanx style="verb">ireg-name</spanx>
production.</t>

<t>Care should be taken to %-encode the directory and file segments
of <spanx style="verb">path-absolute</spanx> according to <xref target="RFC3986"/> for URIs or
<spanx style="verb">ipath-absolute</spanx> <xref target="RFC3987"/> for IRIs.</t>

<t>Not all archive formats have an explicit
character encoding specified for their paths.
If no such information is available for the archive format,
implementations MAY assume that the path component
is encoded with UTF-8 <xref target="RFC2279"/>.</t>

<t>Some archive formats have case-insensitive paths, in
which cases it is RECOMMENDED to preserve the casing
as expressed in the archive.</t>

</section>
<section anchor="interoperability" title="Interoperability considerations">

<t>As multiple authorities are possible for the same
archive (<xref target="authority"></xref>), and path interpretation
might vary, there can be interoperability challenges when
exchanging arcp URIs between implementations. Some considerations:</t>

<t><list style="numbers">
  <t>Two implementations describe the same archive
  (e.g. stored in the same local file path), but using
  different random-based UUID authorities. The implementations may
  need to detect equality of the two UUIDs out of band.</t>
  <t>Two implementations describe an archive retrieved
  from the same URL, with the same location-based UUID authority,
  but retrieved at different times. The implementations might disagree
  about the content of the archive.</t>
  <t>Two implementations describe an archive retrieved
  from the same URL, with the same location-based UUID authority, but retrieved
  using different content negotiation resulting in different
  archive formats. The implementations may disagree
  about path encoding, file name casing or hierarchy.</t>
  <t>Two implementations describe the same archive bytestream
  using the hash-based authority, but they have used
  two different hash algorithms. The implementations may
  need to negotiate to a common hash algorithm.</t>
  <t>Two implementations access the same archive,
  which contain file paths with Unicode characters,
  but extracted to two different file systems. Limitations
  and conventions for file names in the local file system
  (such as Unicode normalization, case insensitivity, total path length)
  may result in the implementations having
  inconsistent or inaccessible paths.</t>
</list></t>

</section>
<section anchor="security" title="Security Considerations">

<t>As when handling any content, extra care should be taken when
consuming archives and arcp URIs from unknown sources.</t>

<t>Archives might contain malicious or inappropriate content or
file paths.</t>

<t>An archive could contain compressed files that expand to
fill all available disk space.</t>

<t>A maliciously crafted archive could contain paths with characters
(e.g. backspace) which could make an arcp URI invalid or
misleading if used unescaped.</t>

<t>A maliciously crafted archive could contain paths with
character combinations (e.g. combined Unicode sequences,
text orientation change) that cause the arcp URI to be
very long or disruptive when rendered in an
user interface.</t>

<t>An archive might contain symbolic links that, if
extracted to a local file system, might address files
outside the archive’s directory structure. Implementations SHOULD
detect such links and prevent outside access.</t>

<t>An maliciously crafted arcp URI might contain <spanx style="verb">../</spanx> path segments,
which if naively converted to a <spanx style="verb">file:///</spanx> URI might address
files outside the archive’s directory structure. Implementations
SHOULD perform Path Segment Normalization <xref target="RFC3986"/>
before converting arcp URIs.</t>

<t>In particular for IRIs, an archive might contain multiple
paths with similar-looking characters or with different
Unicode combine sequences, which could be used to mislead users.</t>

<t>An URI hyperlink might use or guess an arcp URI authority
to attempt to climb into a different archive for
malicious purposes. Applications SHOULD employ
Same Orgin policy <xref target="RFC6454"/> checks if
resolving cross-references is not desired.</t>

<t>While a UUID or hash-based authority provide some level of
information hiding of an archive’s origin, this should not
be relied upon for access control or anonymisation. Implementors
should keep in mind that such authority components in many
cases can be predictably generated by third-parties, for
instance using dictionary attacks.</t>

</section>
<section anchor="iana" title="IANA Considerations">

<t>This specification requests that IANA registers the following
URI scheme according to the provisions of <xref target="RFC7595"/>.</t>

<t>Scheme name: arcp</t>

<t>Status: provisional</t>

<t>Applications/protocols that use this protocol:
  Hypermedia-consuming application that handle archives
  or packages.</t>

<t>Contact: Stian Soiland-Reyes <eref target="mailto:stain@apache.org">stain@apache.org</eref></t>

<t>Change controller: Stian Soiland-Reyes</t>

</section>


  </middle>

  <back>

    <references title='Normative References'>





<reference  anchor="RFC2119" target='https://www.rfc-editor.org/info/rfc2119'>
<front>
<title>Key words for use in RFCs to Indicate Requirement Levels</title>
<author initials='S.' surname='Bradner' fullname='S. Bradner'><organization /></author>
<date year='1997' month='March' />
<abstract><t>In many standards track documents several words are used to signify the requirements in the specification.  These words are often capitalized. This document defines these words as they should be interpreted in IETF documents.  This document specifies an Internet Best Current Practices for the Internet Community, and requests discussion and suggestions for improvements.</t></abstract>
</front>
<seriesInfo name='BCP' value='14'/>
<seriesInfo name='RFC' value='2119'/>
<seriesInfo name='DOI' value='10.17487/RFC2119'/>
</reference>



<reference  anchor="RFC2279" target='https://www.rfc-editor.org/info/rfc2279'>
<front>
<title>UTF-8, a transformation format of ISO 10646</title>
<author initials='F.' surname='Yergeau' fullname='F. Yergeau'><organization /></author>
<date year='1998' month='January' />
<abstract><t>UTF-8, the object of this memo, has the characteristic of preserving the full US-ASCII range, providing compatibility with file systems, parsers and other software that rely on US-ASCII values but are transparent to other values. This memo updates and replaces RFC 2044, in particular addressing the question of versions of the relevant standards. [STANDARDS-TRACK]</t></abstract>
</front>
<seriesInfo name='RFC' value='2279'/>
<seriesInfo name='DOI' value='10.17487/RFC2279'/>
</reference>



<reference  anchor="RFC2483" target='https://www.rfc-editor.org/info/rfc2483'>
<front>
<title>URI Resolution Services Necessary for URN Resolution</title>
<author initials='M.' surname='Mealling' fullname='M. Mealling'><organization /></author>
<author initials='R.' surname='Daniel' fullname='R. Daniel'><organization /></author>
<date year='1999' month='January' />
<abstract><t>Retrieving the resource identified by a Uniform Resource Identifier (URI) is only one of the operations that can be performed on a URI.  One might also ask for and get a list of other identifiers that are aliases for the original URI or a bibliographic description of the resource the URI denotes, for example. This applies to both Uniform Resource Names (URNs) and Uniform Resource Locators (URLs). Uniform Resource Characteristics (URCs) are discussed in this document but only as descriptions of resources rather than identifiers.  This memo defines an Experimental Protocol for the Internet community.</t></abstract>
</front>
<seriesInfo name='RFC' value='2483'/>
<seriesInfo name='DOI' value='10.17487/RFC2483'/>
</reference>



<reference  anchor="RFC3986" target='https://www.rfc-editor.org/info/rfc3986'>
<front>
<title>Uniform Resource Identifier (URI): Generic Syntax</title>
<author initials='T.' surname='Berners-Lee' fullname='T. Berners-Lee'><organization /></author>
<author initials='R.' surname='Fielding' fullname='R. Fielding'><organization /></author>
<author initials='L.' surname='Masinter' fullname='L. Masinter'><organization /></author>
<date year='2005' month='January' />
<abstract><t>A Uniform Resource Identifier (URI) is a compact sequence of characters that identifies an abstract or physical resource.  This specification defines the generic URI syntax and a process for resolving URI references that might be in relative form, along with guidelines and security considerations for the use of URIs on the Internet.  The URI syntax defines a grammar that is a superset of all valid URIs, allowing an implementation to parse the common components of a URI reference without knowing the scheme-specific requirements of every possible identifier.  This specification does not define a generative grammar for URIs; that task is performed by the individual specifications of each URI scheme.  [STANDARDS-TRACK]</t></abstract>
</front>
<seriesInfo name='STD' value='66'/>
<seriesInfo name='RFC' value='3986'/>
<seriesInfo name='DOI' value='10.17487/RFC3986'/>
</reference>



<reference  anchor="RFC3987" target='https://www.rfc-editor.org/info/rfc3987'>
<front>
<title>Internationalized Resource Identifiers (IRIs)</title>
<author initials='M.' surname='Duerst' fullname='M. Duerst'><organization /></author>
<author initials='M.' surname='Suignard' fullname='M. Suignard'><organization /></author>
<date year='2005' month='January' />
<abstract><t>This document defines a new protocol element, the Internationalized  Resource Identifier (IRI), as a complement of the Uniform Resource  Identifier (URI). An IRI is a sequence of characters from the  Universal Character Set (Unicode/ISO 10646). A mapping from IRIs to   URIs is defined, which means that IRIs can be used instead of URIs,  where appropriate, to identify resources.</t><t> The approach of defining a new protocol element was chosen instead of extending or changing the definition of URIs.  This was done in order  to allow a clear distinction and to avoid incompatibilities with  existing software. Guidelines are provided for the use and deployment of IRIs in various protocols, formats, and software components that currently deal with URIs.</t></abstract>
</front>
<seriesInfo name='RFC' value='3987'/>
<seriesInfo name='DOI' value='10.17487/RFC3987'/>
</reference>



<reference  anchor="RFC4086" target='https://www.rfc-editor.org/info/rfc4086'>
<front>
<title>Randomness Requirements for Security</title>
<author initials='D.' surname='Eastlake 3rd' fullname='D. Eastlake 3rd'><organization /></author>
<author initials='J.' surname='Schiller' fullname='J. Schiller'><organization /></author>
<author initials='S.' surname='Crocker' fullname='S. Crocker'><organization /></author>
<date year='2005' month='June' />
<abstract><t>Security systems are built on strong cryptographic algorithms that foil pattern analysis attempts.  However, the security of these systems is dependent on generating secret quantities for passwords, cryptographic keys, and similar quantities.  The use of pseudo-random processes to generate secret quantities can result in pseudo-security. A sophisticated attacker may find it easier to reproduce the environment that produced the secret quantities and to search the resulting small set of possibilities than to locate the quantities in the whole of the potential number space.</t><t>Choosing random quantities to foil a resourceful and motivated adversary is surprisingly difficult.  This document points out many pitfalls in using poor entropy sources or traditional pseudo-random number generation techniques for generating such quantities.  It recommends the use of truly random hardware techniques and shows that the existing hardware on many systems can be used for this purpose. It provides suggestions to ameliorate the problem when a hardware solution is not available, and it gives examples of how large such quantities need to be for some applications.  This document specifies an Internet Best Current Practices for the Internet Community, and requests discussion and suggestions for improvements.</t></abstract>
</front>
<seriesInfo name='BCP' value='106'/>
<seriesInfo name='RFC' value='4086'/>
<seriesInfo name='DOI' value='10.17487/RFC4086'/>
</reference>



<reference  anchor="RFC4122" target='https://www.rfc-editor.org/info/rfc4122'>
<front>
<title>A Universally Unique IDentifier (UUID) URN Namespace</title>
<author initials='P.' surname='Leach' fullname='P. Leach'><organization /></author>
<author initials='M.' surname='Mealling' fullname='M. Mealling'><organization /></author>
<author initials='R.' surname='Salz' fullname='R. Salz'><organization /></author>
<date year='2005' month='July' />
<abstract><t>This specification defines a Uniform Resource Name namespace for UUIDs (Universally Unique IDentifier), also known as GUIDs (Globally Unique IDentifier).  A UUID is 128 bits long, and can guarantee uniqueness across space and time.  UUIDs were originally used in the Apollo Network Computing System and later in the Open Software Foundation\'s (OSF) Distributed Computing Environment (DCE), and then in Microsoft Windows platforms.</t><t>This specification is derived from the DCE specification with the kind permission of the OSF (now known as The Open Group).  Information from earlier versions of the DCE specification have been incorporated into this document.  [STANDARDS-TRACK]</t></abstract>
</front>
<seriesInfo name='RFC' value='4122'/>
<seriesInfo name='DOI' value='10.17487/RFC4122'/>
</reference>



<reference  anchor="RFC5785" target='https://www.rfc-editor.org/info/rfc5785'>
<front>
<title>Defining Well-Known Uniform Resource Identifiers (URIs)</title>
<author initials='M.' surname='Nottingham' fullname='M. Nottingham'><organization /></author>
<author initials='E.' surname='Hammer-Lahav' fullname='E. Hammer-Lahav'><organization /></author>
<date year='2010' month='April' />
<abstract><t>This memo defines a path prefix for &quot;well-known locations&quot;, &quot;/.well-known/&quot;, in selected Uniform Resource Identifier (URI) schemes.   [STANDARDS-TRACK]</t></abstract>
</front>
<seriesInfo name='RFC' value='5785'/>
<seriesInfo name='DOI' value='10.17487/RFC5785'/>
</reference>



<reference  anchor="RFC6454" target='https://www.rfc-editor.org/info/rfc6454'>
<front>
<title>The Web Origin Concept</title>
<author initials='A.' surname='Barth' fullname='A. Barth'><organization /></author>
<date year='2011' month='December' />
<abstract><t>This document defines the concept of an &quot;origin&quot;, which is often used as the scope of authority or privilege by user agents.  Typically, user agents isolate content retrieved from different origins to prevent malicious web site operators from interfering with the operation of benign web sites.  In addition to outlining the principles that underlie the concept of origin, this document details how to determine the origin of a URI and how to serialize an origin into a string.  It also defines an HTTP header field, named &quot;Origin&quot;, that indicates which origins are associated with an HTTP request.   [STANDARDS-TRACK]</t></abstract>
</front>
<seriesInfo name='RFC' value='6454'/>
<seriesInfo name='DOI' value='10.17487/RFC6454'/>
</reference>



<reference  anchor="RFC6920" target='https://www.rfc-editor.org/info/rfc6920'>
<front>
<title>Naming Things with Hashes</title>
<author initials='S.' surname='Farrell' fullname='S. Farrell'><organization /></author>
<author initials='D.' surname='Kutscher' fullname='D. Kutscher'><organization /></author>
<author initials='C.' surname='Dannewitz' fullname='C. Dannewitz'><organization /></author>
<author initials='B.' surname='Ohlman' fullname='B. Ohlman'><organization /></author>
<author initials='A.' surname='Keranen' fullname='A. Keranen'><organization /></author>
<author initials='P.' surname='Hallam-Baker' fullname='P. Hallam-Baker'><organization /></author>
<date year='2013' month='April' />
<abstract><t>This document defines a set of ways to identify a thing (a digital object in this case) using the output from a hash function.  It specifies a new URI scheme for this purpose, a way to map these to HTTP URLs, and binary and human-speakable formats for these names. The various formats are designed to support, but not require, a strong link to the referenced object, such that the referenced object may be authenticated to the same degree as the reference to it.  The reason for this work is to standardise current uses of hash outputs in URLs and to support new information-centric applications and other uses of hash outputs in protocols.</t></abstract>
</front>
<seriesInfo name='RFC' value='6920'/>
<seriesInfo name='DOI' value='10.17487/RFC6920'/>
</reference>



<reference  anchor="RFC7595" target='https://www.rfc-editor.org/info/rfc7595'>
<front>
<title>Guidelines and Registration Procedures for URI Schemes</title>
<author initials='D.' surname='Thaler' fullname='D. Thaler' role='editor'><organization /></author>
<author initials='T.' surname='Hansen' fullname='T. Hansen'><organization /></author>
<author initials='T.' surname='Hardie' fullname='T. Hardie'><organization /></author>
<date year='2015' month='June' />
<abstract><t>This document updates the guidelines and recommendations, as well as the IANA registration processes, for the definition of Uniform Resource Identifier (URI) schemes.  It obsoletes RFC 4395.</t></abstract>
</front>
<seriesInfo name='BCP' value='35'/>
<seriesInfo name='RFC' value='7595'/>
<seriesInfo name='DOI' value='10.17487/RFC7595'/>
</reference>




    </references>

    <references title='Informative References'>





<reference  anchor="RFC2046" target='https://www.rfc-editor.org/info/rfc2046'>
<front>
<title>Multipurpose Internet Mail Extensions (MIME) Part Two: Media Types</title>
<author initials='N.' surname='Freed' fullname='N. Freed'><organization /></author>
<author initials='N.' surname='Borenstein' fullname='N. Borenstein'><organization /></author>
<date year='1996' month='November' />
<abstract><t>This second document defines the general structure of the MIME media typing system and defines an initial set of media types.  [STANDARDS-TRACK]</t></abstract>
</front>
<seriesInfo name='RFC' value='2046'/>
<seriesInfo name='DOI' value='10.17487/RFC2046'/>
</reference>



<reference  anchor="RFC4648" target='https://www.rfc-editor.org/info/rfc4648'>
<front>
<title>The Base16, Base32, and Base64 Data Encodings</title>
<author initials='S.' surname='Josefsson' fullname='S. Josefsson'><organization /></author>
<date year='2006' month='October' />
<abstract><t>This document describes the commonly used base 64, base 32, and base 16 encoding schemes.  It also discusses the use of line-feeds in encoded data, use of padding in encoded data, use of non-alphabet characters in encoded data, use of different encoding alphabets, and canonical encodings.  [STANDARDS-TRACK]</t></abstract>
</front>
<seriesInfo name='RFC' value='4648'/>
<seriesInfo name='DOI' value='10.17487/RFC4648'/>
</reference>



<reference  anchor="RFC6570" target='https://www.rfc-editor.org/info/rfc6570'>
<front>
<title>URI Template</title>
<author initials='J.' surname='Gregorio' fullname='J. Gregorio'><organization /></author>
<author initials='R.' surname='Fielding' fullname='R. Fielding'><organization /></author>
<author initials='M.' surname='Hadley' fullname='M. Hadley'><organization /></author>
<author initials='M.' surname='Nottingham' fullname='M. Nottingham'><organization /></author>
<author initials='D.' surname='Orchard' fullname='D. Orchard'><organization /></author>
<date year='2012' month='March' />
<abstract><t>A URI Template is a compact sequence of characters for describing a range of Uniform Resource Identifiers through variable expansion. This specification defines the URI Template syntax and the process for expanding a URI Template into a URI reference, along with guidelines for the use of URI Templates on the Internet.   [STANDARDS-TRACK]</t></abstract>
</front>
<seriesInfo name='RFC' value='6570'/>
<seriesInfo name='DOI' value='10.17487/RFC6570'/>
</reference>



<reference  anchor="RFC6839" target='https://www.rfc-editor.org/info/rfc6839'>
<front>
<title>Additional Media Type Structured Syntax Suffixes</title>
<author initials='T.' surname='Hansen' fullname='T. Hansen'><organization /></author>
<author initials='A.' surname='Melnikov' fullname='A. Melnikov'><organization /></author>
<date year='2013' month='January' />
<abstract><t>A content media type name sometimes includes partitioned meta- information distinguished by a structured syntax to permit noting an attribute of the media as a suffix to the name.  This document defines several structured syntax suffixes for use with media type registrations.  In particular, it defines and registers the &quot;+json&quot;, &quot;+ber&quot;, &quot;+der&quot;, &quot;+fastinfoset&quot;, &quot;+wbxml&quot; and &quot;+zip&quot; structured syntax suffixes, and provides a media type structured syntax suffix registration form for the &quot;+xml&quot; structured syntax suffix.  This document  is not an Internet Standards Track specification; it is published for  informational purposes.</t></abstract>
</front>
<seriesInfo name='RFC' value='6839'/>
<seriesInfo name='DOI' value='10.17487/RFC6839'/>
</reference>



<reference  anchor="RFC8089" target='https://www.rfc-editor.org/info/rfc8089'>
<front>
<title>The &quot;file&quot; URI Scheme</title>
<author initials='M.' surname='Kerwin' fullname='M. Kerwin'><organization /></author>
<date year='2017' month='February' />
<abstract><t>This document provides a more complete specification of the &quot;file&quot; Uniform Resource Identifier (URI) scheme and replaces the very brief definition in Section 3.10 of RFC 1738.</t><t>It defines a common syntax that is intended to interoperate across the broad spectrum of existing usages.  At the same time, it notes some other current practices around the use of file URIs.</t></abstract>
</front>
<seriesInfo name='RFC' value='8089'/>
<seriesInfo name='DOI' value='10.17487/RFC8089'/>
</reference>



<reference anchor="I-D.draft-kunze-bagit-14">
<front>
<title>The BagIt File Packaging Format (V0.97)</title>

<author initials='J' surname='Kunze' fullname='John Kunze'>
    <organization />
</author>

<author initials='J' surname='Littman' fullname='Justin Littman'>
    <organization />
</author>

<author initials='L' surname='Madden' fullname='Liz Madden'>
    <organization />
</author>

<author initials='E' surname='Summers' fullname='Ed Summers'>
    <organization />
</author>

<author initials='A' surname='Boyko' fullname='Andy Boyko'>
    <organization />
</author>

<author initials='B' surname='Vargas' fullname='Brian Vargas'>
    <organization />
</author>

<date month='October' day='21' year='2016' />

<abstract><t>This document specifies BagIt, a hierarchical file packaging format for storage and transfer of arbitrary digital content.  A "bag" has just enough structure to enclose descriptive "tags" and a "payload" but does not require knowledge of the payload's internal semantics. This BagIt format should be suitable for disk-based or network-based storage and transfer.  BagIt is widely used in the practice of digital preservation.</t></abstract>

</front>

<seriesInfo name='Internet-Draft' value='draft-kunze-bagit-14' />
<format type='TXT'
        target='http://www.ietf.org/internet-drafts/draft-kunze-bagit-14.txt' />
</reference>



<reference anchor="W3C.NOTE-app-uri-20150723"
           target='http://www.w3.org/TR/2015/NOTE-app-uri-20150723'>
<front>
<title>The app: URL Scheme</title>

<author initials='M.' surname='Caceres' fullname='Marcos Caceres'>
    <organization />
</author>

<date month='July' day='23' year='2015' />
</front>

<seriesInfo name='World Wide Web Consortium NOTE' value='NOTE-app-uri-20150723' />
<format type='HTML' target='http://www.w3.org/TR/2015/NOTE-app-uri-20150723' />
</reference>



<reference anchor="W3C.NOTE-widgets-uri-20120313"
           target='http://www.w3.org/TR/2012/NOTE-widgets-uri-20120313'>
<front>
<title>Widget URI scheme</title>

<author initials='M.' surname='Caceres' fullname='Marcos Caceres'>
    <organization />
</author>

<date month='March' day='13' year='2012' />
</front>

<seriesInfo name='World Wide Web Consortium NOTE' value='NOTE-widgets-uri-20120313' />
<format type='HTML' target='http://www.w3.org/TR/2012/NOTE-widgets-uri-20120313' />
</reference>



<reference anchor="W3C.REC-ldp-20150226"
           target='http://www.w3.org/TR/2015/REC-ldp-20150226'>
<front>
<title>Linked Data Platform 1.0</title>

<author initials='S.' surname='Speicher' fullname='Steve Speicher'>
    <organization />
</author>

<author initials='J.' surname='Arwe' fullname='John Arwe'>
    <organization />
</author>

<author initials='A.' surname='Malhotra' fullname='Ashok Malhotra'>
    <organization />
</author>

<date month='February' day='26' year='2015' />
</front>

<seriesInfo name='World Wide Web Consortium Recommendation' value='REC-ldp-20150226' />
<format type='HTML' target='http://www.w3.org/TR/2015/REC-ldp-20150226' />
</reference>



<reference anchor="W3C.WD-appmanifest-20180118"
           target='https://www.w3.org/TR/2018/WD-appmanifest-20180118'>
<front>
<title>Web App Manifest</title>

<author initials='M.' surname='Caceres' fullname='Marcos Caceres'>
    <organization />
</author>

<author initials='K.' surname='Christiansen' fullname='Kenneth Christiansen'>
    <organization />
</author>

<author initials='M.' surname='Lamouri' fullname='Mounir Lamouri'>
    <organization />
</author>

<author initials='A.' surname='Kostiainen' fullname='Anssi Kostiainen'>
    <organization />
</author>

<author initials='R.' surname='Dolin' fullname='Rob Dolin'>
    <organization />
</author>

<date month='January' day='18' year='2018' />
</front>

<seriesInfo name='World Wide Web Consortium WD' value='WD-appmanifest-20180118' />
<format type='HTML' target='https://www.w3.org/TR/2018/WD-appmanifest-20180118' />
</reference>


<reference anchor="FirefoxOS" target="https://developer.mozilla.org/en-US/docs/Archive/B2G_OS/Security/Security_model#Packaged_Apps">
  <front>
    <title>Firefox OS security overview</title>
    <author >
      <organization>Mozilla Firefox</organization>
    </author>
    <date year="2017" month="February" day="27"/>
  </front>
  <seriesInfo name="MDN" value="Mozilla Developer Network Web Docs"/>
</reference>
<reference anchor="ROBundle" target="https://w3id.org/bundle/">
  <front>
    <title>Research Object Bundle 1.0</title>
    <author initials="S." surname="Soiland-Reyes" fullname="Stian Soiland-Reyes">
      <organization></organization>
    </author>
    <author initials="M." surname="Gamble" fullname="Matthew Gamble">
      <organization></organization>
    </author>
    <author initials="R." surname="Haines" fullname="Robert Haines">
      <organization></organization>
    </author>
    <date year="2014" month="November"/>
  </front>
  <seriesInfo name="Zenodo" value="report"/>
  <seriesInfo name="DOI" value="10.5281/zenodo.12586"/>
</reference>


    </references>


<section anchor="examples" title="Examples">

<section anchor="sandboxing" title="Sandboxing base URI">

<t>An document store application has received a file
<spanx style="verb">document.tar.gz</spanx> which content will be checked for consistency.</t>

<t>For sandboxing purposes it generates a UUID v4
<spanx style="verb">32a423d6-52ab-47e3-a9cd-54f418a48571</spanx> using a pseudo-random generator.
The arcp base URI is thus:</t>

<figure><artwork><![CDATA[
arcp://uuid,32a423d6-52ab-47e3-a9cd-54f418a48571/
]]></artwork></figure>

<t>The archive contains the files:</t>

<t><list style="symbols">
  <t><spanx style="verb">./doc.html</spanx>  which links to <spanx style="verb">css/base.css</spanx></t>
  <t><spanx style="verb">./css/base.css</spanx>  which links to <spanx style="verb">../fonts/Foo.woff</spanx></t>
  <t><spanx style="verb">./fonts/Foo.woff</spanx></t>
</list></t>

<t>The application generates the corresponding arcp URIs and uses those for URI resolutions to list resources and their hyperlinks:</t>

<figure><artwork><![CDATA[
arcp://uuid,32a423d6-52ab-47e3-a9cd-54f418a48571/doc.html
  -> arcp://uuid,32a423d6-52ab-47e3-a9cd-54f418a48571/css/base.css
arcp://uuid,32a423d6-52ab-47e3-a9cd-54f418a48571/css/base.css
  -> arcp://uuid,32a423d6-52ab-47e3-a9cd-54f418a48571/fonts/Foo.woff
arcp://uuid,32a423d6-52ab-47e3-a9cd-54f418a48571/fonts/Foo.woff
]]></artwork></figure>

<t>The application is now confident that all hyperlinked files are
indeed present in the archive. In its database it notes which <spanx style="verb">tar.gz</spanx> file
corresponds to UUID <spanx style="verb">32a423d6-52ab-47e3-a9cd-54f418a48571</spanx>.</t>

<t>If the application had encountered a malicious hyperlink
<spanx style="verb">../../../outside.txt</spanx> it would first resolve it to
the absolute URI &lt;arcp://uuid,32a423d6-52ab-47e3-a9cd-54f418a48571/outside.txt&gt; and
conclude from the “Not Found” error that the path <spanx style="verb">/outside.txt</spanx> was not
present in the archive.</t>

</section>
<section anchor="location-based" title="Location-based">

<t>A web crawler is about to index the content of the URL
<spanx style="verb">http://example.com/data.zip</spanx> and need to generate absolute URIs
as it continues crawling inside the individual resources of the archive.</t>

<t>The application generates a UUID v5 based on the
URL namespace <spanx style="verb">6ba7b811-9dad-11d1-80b4-00c04fd430c8</spanx> and
the URL to the zip file:</t>

<figure><artwork><![CDATA[
>>> uuid.uuid5(uuid.NAMESPACE_URL, "http://example.com/data.zip")
UUID('b7749d0b-0e47-5fc4-999d-f154abe68065')
]]></artwork></figure>

<t>Thus the location-based arcp URI for indexing the ZIP content is</t>

<figure><artwork><![CDATA[
arcp://uuid,b7749d0b-0e47-5fc4-999d-f154abe68065/
]]></artwork></figure>

<t>Listing all directories and files in the ZIP, the crawler finds the URIs:</t>

<figure><artwork><![CDATA[
arcp://uuid,b7749d0b-0e47-5fc4-999d-f154abe68065/
arcp://uuid,b7749d0b-0e47-5fc4-999d-f154abe68065/pics/
arcp://uuid,b7749d0b-0e47-5fc4-999d-f154abe68065/pics/flower.jpeg
]]></artwork></figure>

<t>When the application encounters <spanx style="verb">http://example.com/data.zip</spanx> 
some time later it can recalculate the same base arcp URI.
This time the ZIP file has been modified upstream and the crawler 
finds additionally:</t>

<figure><artwork><![CDATA[
arcp://uuid,b7749d0b-0e47-5fc4-999d-f154abe68065/pics/cloud.jpeg
]]></artwork></figure>

<t>If files had been removed from the updated ZIP file the
crawler can simply remove those from its database,
as it used the same arcp base URI as in last crawl.</t>

</section>
<section anchor="hash-based" title="Hash-based">

<t>A repository where users can annotate
content of open source software distributions 
needs to avoid duplication, as users tend to 
upload <spanx style="verb">foo-1.2.tar</spanx> multiple times.</t>

<t>The repository calculates the <spanx style="verb">sha-256</spanx> checksum of the uploaded
file to be in hexadecimal:</t>

<figure><artwork><![CDATA[
7f83b1657ff1fc53b92dc18148a1d65dfc2d4b1fa3d677284addd200126d9069
]]></artwork></figure>

<t>The <spanx style="verb">base64url</spanx> encoding <xref target="RFC4648"/> of the binary version of the checksum is:</t>

<figure><artwork><![CDATA[
f4OxZX_x_FO5LcGBSKHWXfwtSx-j1ncoSt3SABJtkGk
]]></artwork></figure>

<t>The corresponding <spanx style="verb">alg-val</spanx> authority <xref target="RFC6920"/> is thus:</t>

<figure><artwork><![CDATA[
sha-256;f4OxZX_x_FO5LcGBSKHWXfwtSx-j1ncoSt3SABJtkGk
]]></artwork></figure>

<t>From this the hash-based arcp base URL is:</t>

<figure><artwork><![CDATA[
arcp://ni,sha-256;f4OxZX_x_FO5LcGBSKHWXfwtSx-j1ncoSt3SABJtkGk/
]]></artwork></figure>

<t>The repository adds annotations for
detected source code files within the archive.</t>

<t>A client is browsing the annotations and discovers:</t>

<figure><artwork><![CDATA[
arcp://ni,sha-256;f4OxZX_x_FO5LcGBSKHWXfwtSx-j1ncoSt3SABJtkGk/src/luhn.c
]]></artwork></figure>

<t>The client constructs the corresponding <spanx style="verb">ni</spanx> URI <xref target="RFC6920"/>:</t>

<figure><artwork><![CDATA[
ni:///sha-256;f4OxZX_x_FO5LcGBSKHWXfwtSx-j1ncoSt3SABJtkGk/
]]></artwork></figure>

<t>To retrieve the archive from <spanx style="verb">repo.example.com</spanx>, 
the client resolve the corresponding <spanx style="verb">.well-known</spanx> URI <xref target="RFC5785"/>:</t>

<figure><artwork><![CDATA[
http://repo.example.com/.well-known/
    ni/sha-256/f4OxZX_x_FO5LcGBSKHWXfwtSx-j1ncoSt3SABJtkGk/
]]></artwork></figure>

<t>After the client verifies the corresponding <spanx style="verb">sha-256</spanx> 
checksum it reads the path <spanx style="verb">/src/luhn.c</spanx> from the retrieved
archive.</t>

</section>
<section anchor="bagit" title="Archives that are not files">

<t>An application is storing BagIt archives
<xref target="I-D.draft-kunze-bagit-14"/> on a shared file system, using structured
“bag” folders and manifests rather than individual archive files.</t>

<t>The BagIt payload manifest <spanx style="verb">/gfs/bags/scan15/manifest-md5.txt</spanx> lists the files:</t>

<figure><artwork><![CDATA[
49afbd86a1ca9f34b677a3f09655eae9 data/27613-h/q172.png
408ad21d50cef31da4df6d9ed81b01a7 data/27613-h/q172.txt
]]></artwork></figure>

<t>The application generates a random UUID v4
<spanx style="verb">ff2d5a82-7142-4d3f-b8cc-3e662d6de756</spanx> and adds the corresponding
<spanx style="verb">urn:uuid</spanx> UUID to the bag metadata file <spanx style="verb">/gfs/bags/scan15/bag-info.txt</spanx></t>

<figure><artwork><![CDATA[
External-Identifier: urn:uuid:ff2d5a82-7142-4d3f-b8cc-3e662d6de756/
]]></artwork></figure>

<t>It then generates arcp URIs for the files listed in the manifest:</t>

<figure><artwork><![CDATA[
arcp://uuid,ff2d5a82-7142-4d3f-b8cc-3e662d6de756/data/27613-h/q172.png
arcp://uuid,ff2d5a82-7142-4d3f-b8cc-3e662d6de756/data/27613-h/q172.txt
]]></artwork></figure>

<t>When a different application on the same shared file system encounter
these arcp URIs, it can match them to the correct bag folder by
inspecting the <spanx style="verb">External-Identifier</spanx> metadata.</t>

</section>
<section anchor="ldp" title="Linked Data containers which are not on the web">

<t>An application exposes in-memory objects
of an Address Book as a
Linked Data Platform container <xref target="W3C.REC-ldp-20150226"/>,
but addressing the container using arcp URIs instead of
http to avoid network exposure.</t>

<t>The arcp URIs are used in conjuction with a generic
LDP client library (developed for http), but connected
to the application’s URI resolution mechanism.</t>

<t>The application generates a new random UUID v4
<spanx style="verb">12f89f9c-e6ca-4032-ae73-46b68c2b415a</spanx> for the
address book, and provides the corresponding arcp URI
to the LDP client:</t>

<figure><artwork><![CDATA[
arcp://uuid,12f89f9c-e6ca-4032-ae73-46b68c2b415a/
]]></artwork></figure>

<t>The LDP client resolves the container with content negotiation
for the <spanx style="verb">text/turtle</spanx> media type, and receives:</t>

<figure><artwork><![CDATA[
@base <arcp://uuid,12f89f9c-e6ca-4032-ae73-46b68c2b415a/>.
@prefix ldp: <http://www.w3.org/ns/ldp#>.
@prefix dcterms: <http://purl.org/dc/terms/>.

<arcp://uuid,12f89f9c-e6ca-4032-ae73-46b68c2b415a/>
  a ldp:BasicContainer;
  dcterms:title "Address book";
  ldp:contains <contact1>, <contact2>.
]]></artwork></figure>

<t>The LDP client resolves the relative URIs to retrieve each of the contacts:</t>

<figure><artwork><![CDATA[
arcp://uuid,12f89f9c-e6ca-4032-ae73-46b68c2b415a/contact1
arcp://uuid,12f89f9c-e6ca-4032-ae73-46b68c2b415a/contact2
]]></artwork></figure>

</section>
<section anchor="packaged" title="Resolution of packaged resources">

<t>A virtual file system driver on a mobile operating system
has mounted several packaged applications for resolving
common resources. An application requests the rendering
framework to resolve a picture to show 
it within a user interface:</t>

<figure><artwork><![CDATA[
<img src="arcp://name,app.example.com/img/logo.png"
         alt="App" />
]]></artwork></figure>

<t>The framework finds the corresponding application
package, installed as <spanx style="verb">app.example.com</spanx>. It then checks 
that the authority <spanx style="verb">name,app.example.com</spanx> is valid to access
according to the Same Origin policies or permissions of the
running application.</t>

<t>The framework resolves <spanx style="verb">/img/logo.png</spanx> from within
that package, and returns an image buffer it already had
cached in memory.</t>

</section>
<section anchor="app-names" title="Sharing using app names">

<t>A photo gallery application on a mobile device uses arcp URIs
for navigation between its UI states.
The gallery is secured so that other applications can’t normally
access its photos.</t>

<t>The application is installed as the app name
<spanx style="verb">gallery.example.org</spanx> as the vendor controls <spanx style="verb">example.org</spanx>,
making the corresponding name-based arcp URI:</t>

<figure><artwork><![CDATA[
arcp://name,gallery.example.org/
]]></artwork></figure>

<t>A user is at the application state which shows the newest photos as thumbnails:</t>

<figure><artwork><![CDATA[
arcp://name,gallery.example.org/photos/?New
]]></artwork></figure>

<t>The user selects a photo, rendered with metadata overlaid:</t>

<figure><artwork><![CDATA[
arcp://name,gallery.example.org/photos/137
]]></artwork></figure>

<t>The user requests to “share” the photo, selecting
<spanx style="verb">messaging.example.com</spanx> which uses a common arcp
URI framework on the device.</t>

<t>The photo gallery registers with the device’s
arcp framework that the chosen <spanx style="verb">messaging.example.com</spanx> 
should get read permission to its <spanx style="verb">/photos/137</spanx> resource.</t>

<t>The sharing function returns a URI Template <xref target="RFC6570"/>:</t>

<figure><artwork><![CDATA[
arcp://name,messaging.example.com/share;+{uri};{+redirect}
]]></artwork></figure>

<t>Filling in the template, the gallery requests to pop up:</t>

<figure><artwork><![CDATA[
arcp://name,messaging.example.com/share
  ;uri=arcp://gallery.example.org/photos/137
  ;redirect=arcp://gallery.example.org/photos/%3fNew
]]></artwork></figure>

<t>The arcp framework checks its registration for <spanx style="verb">messaging.example.com</spanx>
and finds the installed messaging application. It performs permission
checks that other apps are allowed to navigate to its <spanx style="verb">/share</spanx> state.</t>

<t>The messaging app is launched and navigates to its “sharing”
UI, asking the user for a caption.</t>

<t>The messaging app requests the arcp framework to retrieve
the <spanx style="verb">uri</spanx> &lt;arcp://name,gallery.example.org/photos/137&gt;
using content negotiation for an <spanx style="verb">image/jpeg</spanx> representation.</t>

<t>The arcp framework finds the installed photo gallery
<spanx style="verb">gallery.example.org</spanx>, and confirms the read permission.</t>

<t>The photo gallery application returns a scaled down 
JPEG representation after retrieving the photo
from its internal store.</t>

<t>After the messaging app has completed sharing the picture bytestream,
it request the UI framework to navigate to the <spanx style="verb">redirect</spanx> state:</t>

<figure><artwork><![CDATA[
arcp://name,gallery.example.org/photos/?New
]]></artwork></figure>

<t>The UI returns to the original view in the photo gallery.</t>

<t>This example shows that although an arcp URI represents a resource,
it can have different representations or views in
different apps.</t>

</section>
</section>
<section anchor="acknowledgements" title="Acknowledgements">

<t>This specification is inspired by two original URI scheme proposals from W3C,
<spanx style="verb">app</spanx> from <xref target="W3C.NOTE-app-uri-20150723"/>  and <spanx style="verb">widget</spanx> from
<xref target="W3C.NOTE-widgets-uri-20120313"/>.</t>

<t>The <spanx style="verb">app</spanx> URI scheme was used by packaged web apps in Mozilla’s Firefox OS
<xref target="FirefoxOS"/> and to identify resources in
Research Object Bundles <xref target="ROBundle"/>, however the W3C Notes
did not progress further as W3C Recommendation track documents, and their URI
schemes were never formally registered with IANA.</t>

<t>While the focus of the previous proposals was to specify how to resolve
resources from within a packaged application, this specification generalize the
URI scheme to support referencing and identifying resources within any
archive, package or application, and adding flexibility for how resources
can be resolved.</t>

<t>The authors would like to thank Graham Klyne,
Carsten Bormann, Roy T. Fielding, S Moonesamy,
Julian Reschke and Frank Ellermann 
for valuable feedback and suggestions.</t>

</section>


  </back>

<!-- ##markdown-source:
H4sIADtZeFoAA819a3PbSJLg9/oVFerYsOUR+BL17G7vqP1oa8avtezrueno
EIsASGIEAhwAFM3u8Y+533J/bPNVhQII2bJ3Iu4cO9sUiKrKysp3ZiWDIFBV
UqXxuX6/iPVFES6S21ibLNJvTXhj5rF+aIpwta8/vLvUZbiIl7Ey02kR355r
/EJFeZiZJYyPCjOrgjJPUhhdxNu4DPCFYHCoIlPBC6PB8DQYjILBkQrhwTwv
tuc6yWa5UsmqONdVsS6r0WBwNhgpU8TmXP8cZ3FhUnUTbzd5EZ3ry6yKiyyu
gqe4mFJlBWtdmzTPYH5YUa2Sc/1rlYcHusyLqohnJXzaLvHDb0qZdbXIi3Ol
A6XhX5KV5/qqp68Y5uAdAk3f8I6uqsRkHd/mxdxkye+mSvKM8fYhA6wVZVJt
dT7Tr0wGiCoBVHq9BDji6ly/+TiDTeh3uYnoeQivn7dfDvN1ViFiYMoqjvRf
k2we5Uv6Ll6aJD2H+UyS/dmsDIzrASz03bqAnS+qanXe7+dFmET4TX8A/wL4
3zA4Ox2PgrOT4Wlj8696+sn//T9hXDT2/QrOLS+b3zT3/Cr/PUlTo5/kxSov
6KEP4ZIm+DP/J+yFAr8Po/ddX6ksL5Ywy20MZ6O/0++eP9Fy5rg6/DkaDs/4
uw/vnwen8nB0Ig+r+GPVh+mDNCkr+XJ8eigj3l3yo8Oz02N+dOk9OpE14Yzz
ZRaXpS7if66TAig9q2T58cCO/PDh8qk8G45G/Ky3idM0uMnyTcZfHZ2cHvFX
V4BQwF0yT+Sr4/HRmL/KEr0w5SKWJY7PRgOBJJ7DLhir+m2Rh3G0hmPQQD3E
hVfEhTLs5OgMllLIRg0UvoqjxOhqu7IvjgZj2cLUlPHxWDZxPD51WAI0Llcp
sKZAdHQiEP3p92SleQEL7emhoH6WpLEvHOjr08HpmV1snuCJXAZPeywhbtbZ
73FAz4Oh4GJzGJI0AcKAv385fNJ7/eb9s8CsVgGeKkiOo8HJ6LB+eZNEc+Cp
5uv8sLRDRoPDoQx5+fStvPju2ZMgjVY85WgkKNnEUw2LAeFmySwmEsKXf3mK
INiHOOZ0MBwKwp4Diczyj2+uruIQVqy28NQ9O2fOj4skLvFs+G+tXz19XXPP
0/g2TvNVXOjXcQXEfqN/ATie5iGznJNWWhiwHinr0FcivuWRfnMFyzJAOgeh
dJvEG37PFIgyYsASMBfZ1XtLnpUkRpwFH676INTLviiD/k+jn6/fXPXtNt2H
62Uexel3oiei64vVigF34v4Exf3ohKn6jZ6usyglCnnzE328C0t/j7M8ys+B
EUG6VPLw6ZvLcz0c9I5Gp8P+7/RGbzg6Oj32sfAuLmMgpIV+M/1HHFaa19HD
3qATB5tDEZQMWn8H78EXVMHnlEjgxGlVLeKN/tksp7R9X/x6D+377/JpXFT6
BUj55irvev5DxvIDQPM4GA5Bqz5Q+C8IAm2mKD9CUJDvF0mpy1UcJrMkZIkS
xTOYQwNIqkvd16ysJ8iSkx7oTfgvflHqELAwjfW6BNVU5aCtsnJNEg7OagbK
IgtjvQChUyxR/igQW/m6CEF4MYIj3EgSwYosN4wAAONNpoDXUgvlisE50KbU
KF7xv7AgTpjexgwMSCRlZ6hX2iTVIslghVWRzwuzRKkY6hl8ipHHeoIUb5/w
4i0AVeplHC6A2cslrTUn66MCKNU6S/65jklysqBESFawJqgIxKQu8rxC1Y+f
BaQDVebwt6ng1ZQkMw11eCo1QWkRYzegBMWy08jux5uZHuXrCvTHLZgHAI0C
/YcH3ngLDqdC+HIenOahSRnt5RbsjSVg4iLT9mwbR4uqZrUG3V4CmLCtBGBh
Lf8w7s17erOIMzl8BGC5TqtkVZ9nuQ+bt0IIXwPgElCmYEve5kmEQ/bCNFlO
NexiD84mX/qQw2hYH2GAbYG9Z9J0q+GAsirZznBwuZ4G7sCVw2ikp1uP+qzG
6glXLJMIxY9SYEUWebQOidDk3x/fJd7TT+pH759Sr/IpkSvwCYroi5pQS7U0
WzlEjwjLNcggINmy2qYxKHlQS3Rq6voOYrjWf/whJsqnT1o9/HXcG/320Mqp
Ks/TspfE1Yyk1aJapv1iFuLb3wGiEZAABuzvK6DMMiySVQWGb7IEDioJ6hnQ
QtlD8QhEBShU+HBlwGSFzwTsDgMhfMANUYoYd+wDTAL7FQtJCYvgGyBz8nRd
CWvi9MjOW5wfjaDgDRlBvEs0gmCXjkRWOaAzQbTFABOwHJw3MndsEIurFZzg
VT6rNuAVMEcB/5oQYEXw9d1CJnPigcl2AnbMBIXNBBRBb/77hNhhn0gfaHQ9
n8Mh1mJNebRkmYksKgYCOMWxtmqxtj3/Sa/XD8uyPzlQ8FdCkIOMSdM4mzPr
arAszBTs1gX9DVxwbcXMtWrRxFFv+HU0AQOAJkjO4J7ArMQ9zMDshG8Bq8/x
IOER4NuXHMtkvqhIGGQohwGjJDzS7YFKlnyoThaWOk1uQFcgJgGqfrVc9c1w
Ojox8eDw9PioP1H3kZagQBFlTDx4zGCKgmdRwJIMTZYTRPM0n5I8YJF8QJQG
TlMa4be36xQJckrHqEDvAvT1YbDMQeBJ7AgABEwE1BxW4JE6oehEKEiuhox7
8f7VS6Ah9TLJEDNPTWVqEjxwiyHS1U9mflm52f744y4r+NOnA+Irkr/IMr6U
IGUUFnlZBrWSJamaVGs6T0B9CXgyNwgoEFmLwpIsij+yjgUsokZrcjzs+QlR
/IokIuDFZA1d0yQfOfmXqlxYvIOiKBPEepbDPioQ2izUN4sEFkLioZkBtI1B
/6oCiw90G8j5TN4BazSBbTGHAP+CyQLuLx8vgcCvKaeiGwTr5AEcCLP6bVJU
66a+24d9/vIFxcVgowu+LtH9tjoGIbebnYLQA2sqgdkBuaCD0ZwhR09kHImz
rS/qdk0BEi0gWm/IpnpQgRgIzYrMMpTLYLKsU1M47kCjxTLZxLddaBF0t2AR
0eBgywflmqIHDT1uKdNMwS84QITixpU9nQDJZBVnqGf9FWTWZQ5cOUvjj3jO
ot5ZI7ZYsvcFq1Pfz+xESBXSYUomACEN0G2iqNiR+8rafI5sD7RvTCIWeB2U
efAXYZnxwmKgDS8Snn70SGZ79IgoTIU5sFVomaRhhVjASPaAGZKx4w/rVose
I4RQkNDoED2zEpVJgkaZJWMiVrFaSKyqSW9HZSHWInCZ0Dac/Im+XtbOvlAd
uOcgU9QUjESTAvFlcL40uwXYIkTWgd2Cj6yfsLwD9v3jjy5vGeeEV4E/K5Qw
zhqS1+/wl3EUSh/N4nCWpwA/KdywQiL6nFyUA8OAI1gKB3RyQBBLfS1Iu8aj
YX9kUeTrORnGeKCqfaApGs3zhWduIiOQvCQ6AzQtY7QZ9HVo8XB9AAvVlER/
zudFPOc/8WCuBZPXwqRLgyKgJq7aeUpIkou34UtUtm1nCdIEMSibUsp6OTqL
SRrVElt3sVgOp4lqUnjNwLAN/I9CCwqWrXIg4AO9yDcgfAvceAkmD0xdEueI
08iex5q9MBlEwot0P0XF2PJltKGRx0oLrHXYD36ww0rEj7J+WNOORKv8nRdo
0y9NNl+jKCBr3I/BNa1xzyxHdN/EW02BQr336sPV+70D/q9+/YY+v3v2Xx8u
3z17ip+vXly8fOk+KHnj6sWbDy+f1p/qkU/evHr17PVTGgyzXvzvPdJHau/N
2/eXb15fvNzT5Jghb+fhGmFl2yUnMYyxarB68OAMcj/a5VOyTtmuw5gmEbji
iB6oKUDtR94/f27tXLQAy0dPYgJHpfmmJKL2TUaZECloAcRFHAPyhukKFCag
TUwEHMmzyPmJI1SeA3gUFMFQPi7J/37kB7L+3vme/C0EqX/Ve9+hY2fmhJXf
vElkDE2yh0/2/C/tBPhlvy/TckQGPYVfSaAGztn4DVf6zz0NeqfY4jI1hupR
E+A1sCYzhMT5+kbUlcd8hCjERA5qEE/NmaZxrH+9sNP99vA7N/U+jYlikBZp
abV0A8TOxVn6yB7wdRIUdQyAbRgJkuAC1jzd7wgHCHxvYRoADWfbVx1QEYp8
aICgrcN/oFFTJBV6YCC+wfogaQXuFIkScqx3laTMvGePea97chzcFh2O+NA5
8EkWtRvuDQckMLZWbfwahrHhNbbdXXxJm0osJ9C2n5WN/HiLQhCXBhyBMrGW
Sb0YcqU7cORHd+KfMJbA/3j7DTsCaa+L7JxxwrEW0E4oJNYJWJR3EaLpsgMx
26RqdoB9grQiUQNHFYnk4dARWSI2UoRGRVwozFGA2p7Hbe+Lt1JP7HwAhpck
KvpXJk2ihuRQMEsZtySGY+d6wh/1eg1D/4Vpj3+xdfSvej1OD+EL7h/wPz44
2LMpF41DdeOFLIGvTToPAC6Xv2q+AQ/gHVDYAX5UakgoBHiBsD/qCS1BBzXF
wCq7GnSMuOrE2xfLcOYGG8fAFBC6bsitiucamfFJOD47Ckx4MgjGcTQMTo8G
0+D0dDAwRyfHw9NwNlFq1AQDNtIJhOztS3Bg7qiGAyYrFyYYHR1//5cnVyfb
23g9f3b4wfw9efGkHP5t9e5/za5emHjz8eKvN2aQH/1zlJfzUwDqsAUU4q4T
LItOHy7VARfzNMMl82E0J/5oUBxg7m/S02jeEaGpS1RLduAJDkSJNEm6lmP7
noKoYBqZCCm2hgvoeWw340b4nAkWNmZdaQHPLm8DDm7+JPGGzSysbVB7+qJk
CZnF6IeaIgGziG1KXEqr2uBk/AKaPKZBwxaFSO1Sk3kIdjJ6cUlRYvBjhi6Y
moHlzQGY8IZVN6xaT4WSC1UBCi0UhyyvvqCZANMzLRGaA0XczmBXTRS28YNm
/SRpzfoZJL0XWFELqn+vElTOrfS9oVsDZkGSNYLQFPqkgEWSwrFjhDtToA8o
GPcRsVASOKVnKrfUl1iKGAGc9NFVVQS/hC8leC1GO7s7EobFSA2AeklhDs/C
5DBNmK4j1kQIK50yTg9nw3ERTjFTIMFquzqyhiaNH8ZyVqXT6GxY2j93repu
x91qTodCvUEA2E2V4JyNRmGyJKtdMw7fZDGcFiCRZkoqFzx2+/CiOBIaIt2F
npBGx4I86irGOgqzREpANMIOn7EcoQxFY2AHIQhy1cTz5vroPB/oxqPbLOph
/UqeRD1x7AKZb3LQHP0xAJe8Pf5jMMen5Ce0vjj5PUCGKyhMNWnB7xx0F4my
EP//7Jp7NpJPZp65FHj0Fuz+Y7l07V6/9m0maw+VTSqpyjidIRO1mBJNTlNS
PpJJa5N7zrfVXqpEG6E2TOr1KDYX2yxjIxeC6+M4m0/AMC8nmOHtNFkmFgaQ
H6mxOpAt5jj0bOV6XdYCDcGrF3G6KlkUIHvZPERRKmI5thOpRMWXZxSBnMZx
xtY25eYEd5R+8XOSziD01RQLZEriUBDVOoS1aAWr6XImyoCMA9iYtZ3YbWQz
35Cx1jCOwC4jPCRZhKzge17uRAnYattrJNboPGF040gXqBgLwBecGUE8WRfZ
OUIiYVEY0E03va/YxO14Zx8wL+bkxl/Mv+DrXk5uvL+/gwL/IDGYHmGKFhQf
VSDpbL2cAg9Kai0veho31Sb2EGQhxVp4VEDzKO0IDHcvWsrlsXHrsDVZh3bI
2QaNgnadVCQ97wBDkDFAxd9D+/W+uDwiq5wBvAuth1+L1sMOtJbdeM3quJQl
OBvypik4BovWGuY8X34B3S5afk+EwxuAgRrXhDNMnrCzUoKOARvieGpOpqfD
YXAWmSgYDtFrGEzHwWAQDsazaHw4CMFA15xWzTqVHYIOb7zOK+EVju93xOxQ
mds6ilaCZmOwtoQjAgDolkJ8IGvAAuWQafsok5mrLZAiQDiQHNX9JgHjiAyW
HjoWu9RCPs99RQNM7HEK1s1RGq/hxD4oW2aC5Gx7HefZ1hW75SO4F4Bx4qmQ
AssbM0zqY0mJF1G2AYt6BczmMSZd5jiL53mVuIRECVoDPXuQ4lkpxXsAGZMf
qgqw3sIbgNA532KbMtW1g3edrmLTP9TEbHezGldOIbPh+47ZgNW6MOg4Ag9D
SMLnBYqy1wmZB0hY3vF4FjSCj5OAvQbDIz0R73XilBWYI5kNOX35LDuURJaw
eviMdhh30ii7wC0qrQ1XL36RcBC9M+tEbHPgi5qyNtRgLBG1ZECRNLg8p1MQ
Cd78/cKy6wzs/nyeJXgKBPXEE00UJ8ozl6HzSqTqCJPA4+QiBgQ9zM7WBRnx
noidr8HZAdqW0lQSZxQyLEgyxwlzYJGnspVdp4dqOe4gLJGQHaSFRPP09ZW/
YnM9hB9Boj1htpxPxjOOsTSjHYpAYQcDl+aGBzjsdUcu2FCc4do5GqUwVI47
8usB0EOm8bM8731uDqQhjEZs4e0k1C4FRZENGDxpJOxRQnhnAUy/igvCDmYg
Hj1aZ+LGxdGjR84l58g/C/16f1FODh57/CbbWrkqgQo/rqM6o8AccGh6ABQU
uNP4F7sfX/JN/lbY0VqxxHtgoq5NqnYldUec1OM1ZfQj5xY/wuN4hH7WIwD7
keV4gQM5HtztgONVP0hBMlk1p4eH8TQyo2B2Zk6D8fh4FExPxiYYz8IoHJrB
KBqN+o91gMa2i0uspMbLL31pejEHqpYJ7j0mT9MqTGGFZvPPvRp4igLEWSQu
Du7AAdGKEChz93zsnnQWeiL1MK25Ojz2LDq0pvY8JFsIw36p03Ei31yEq7MQ
A+M5pVRpMPcChRcJWlV1CQgTMvo/u5HtpgaoywJq8lIu7etvtM5+UtXZsj4y
m5jnkAdWhiWe4aBceJQczIfRmjVBvE+ncKATW+oSYv0MB3TqBAuqyw7mkiEe
hcd4PUQnXkKRM6m7OVvKotrHd3rfHQGfdhKZa9PrXHCurPnolT+0DRJH/5zv
61Ea3wpkEIvZrslEeC3iDQglnxRhPSo/S37HmCkG5rhy1pWI1UQtVS1AcGSD
dq+A6gO9AvBvIkyavHj//i0Wod/GhQvNxdltUsIQKitgHduaa5OkqeLiH1t5
5FVNIYDRLW+VjPayTOYkQmku5dNzLYgbWbE7Eo5SKLcDEFEzMb49HIdBCcBP
JU+vkixYxkuUARZc8fvhhJYAmTDMSpDNB6ruqiFuWyiEr3K9wtJ9gcVNSOfJ
Jsw5RRWemyStEwsYGAQbVjTBNfgy+nkOPHJt/YyGRbPOxL0YfWGen+Ecu6eg
CTj5yTJDKqZnTVmNAVDYezYHkjK3sBR6XuTWfCX8JI9dRBVwTSVNdVFOV1x7
jGW71brIOsTaw1WOACdSflWHF/d9W9tfHNYseVE6xa4Fj9yCLcFb645UHOru
mev3uqY/vv/0O/5dSyX6y7PyviMsaMmRpcLGbBuXCVqMoriYAEP5S0wPl54v
6XtxsBaesEnTHRWR76YMUF5wqA6ZCaYL4xUbPLsbbykL1eFf4q5mSHyulJPl
vBfobFLjHsLqcBNHe07WISl+IdOPiZA7RM5dGXTemk9ktXjsaVY8rm7Xuba4
cXA8gbxRrtfq5aErXnR3tPYPFIx0yxPktBxeGshKwgUJtDlY08QNtkCrhnHS
uDg4kRKD8ekheMt+BYNfway+fGAo5cVREzOe3S+ksdpOcBpSyLyelfYJzLwE
zKP783lLxJe1Yo2xgV/EyuVeZO6ERA9aOXOyJighJSWz4oBKNXG5XU6xjlVT
ker+vSrOKLzuvAAkgAqVdCVmgeW3nerje0wt+Tm0/OaxR0qYvUC3yfInB9kc
Rzvb6JarzzAm4d/XRMN5lScwEKyl+nGntdRlP11+ruij5c3YnHMjXKPqcM1B
O4Dgud9NsY85fqy158LQLFlwdKNsRHuc8+SrMnVHhEztRN7l6PjcuF67QwG5
CxYS7gFn2cNuP0sARodigg7vxmIsyrgT3ylkoOsvX4wIN4JUYwxSNfYg/AdG
ncWBC6i54iEpQ3fYkRR7bbTUfqdnECFNPQNdSwiwToysimQUy3d3lC3aMj4v
+0+OB4XPubxX4o4ECcCIlfBoBZM1bWaxvrh6cnlJb0q9AId0Ka1Kh6Dibvhs
BTxtxtbNAvJ3Ky+ISHeKLpR4PR+yBOZHlBosGUUd2aQLDon4tRuqUaLwBHdX
FztU5gY91lz/R0CQx22BKLlz0A1zvpaNQZFW3UHDBfFryuTidMnlHK1R3q7p
xUuWGndpdrb4M0r0JWFSKYcC7XBe07UUFCaFpZxLzPSyAPQ9YgweWrvSVSE2
lz7YKb/tinuSKeQkkCJPBvEplyjo8rxoudEJV592ahbaJqqyAFw21KZUfy9V
EeDR17rO3mpqFTOQsiyszDDkd5iyqeibOUZFzR0wjGWoMGPbxVtJ6507eazm
tYvSiy54UUSkQHdvxeLcT/Lqh3e4YPvs07HZaat82SJijYxVJ8RChbs+0Qbc
3dEhdR1nKv5Iuq3pKk3B98bEbuvo8bbxMm7hhx2q95t8x/S0kYI6OmGVpxbV
XwKX1WdCr3iuHpWUspdk84VRMqObSFUj/8g5IQ/JXIPVhodzI1nMhhVacGGF
vpNJpfSQKmBgIzhdiZe18OEUFiJf77Nb9HxwJ98xGmxr/mlvH969PNDNeE0z
r9fcyNbGwz2NUXkoqJLlnVsleoiS0syLGPFtpvlnnU3yKv9fbLG5QcpdIS3W
u+zKYwEvI2uRpqxfVbotT+6kg13USDiTRekBEyCVdbIQ0V4t+5ac46+ieM8t
dlu0+adWpmHr4gJbFodrTr0hYdZYocQVGHM4YrG8F8FbBPJ9JmvnNyciL7xr
Z7ZCo7UvpFCRyeJwOM4Vj3BXZVuqlrvjDFxzd16kB7b2si50kVw0LHaLVqa1
YdxplVaW7ESMUOZYZ87CRO1fUukucyAulNM7fO8nr2AeIg6UmljjruUqMpKg
Xa6NLr4hj6mVzLtvQ5FIuUA8tWiikjl7I/lJU/Vg2Rx/8xmj7oIleX1pGi0x
4ZoDxjJsrcPuIflfX0p0FWAUOHS6QG4mstvi7gG5skcra+z5I0LDJF+Xslsv
0OIkT6FqKmlffEUI7Vx1XEkcRrI3QJdTtX6Os6RsLTkjBvj6RlN1A05cQwNe
cIjVZJ7V3VzLI9maVKUWFEteac59R+w41GXsXN4o40J12OAyKdPYRBKsInt3
nfFdy+ibIfOMPq6OFjJhKKVgOnLkXdIla8wGKow3YD8gF8dhh3afMRoamw93
W6GKfnWLASkMQHIdbFmsV2SQbTjem3GdMJctwBQFmxszwX59rE0Sabr4BALW
o6mGQDC7LHwg88iVR6YJBcKbbt03I3a1De+KCnt3JLWVWAIkHRgkMrOK+Jao
VeZnvuV93XF44m83Nos38SdaynTZiTgQMxYIIzMAbrplgVa4rbtb7RNvRtm2
Ylb49m0rcVHBKKRqP0qiXjFs+rUvEn1vRomTKpC2ox2XmZ8ssg7NgW80tOSE
2MbKYzypTQnSPKcr5Z6bBxPSK7Wyd4qFyd6j9gaTeqE04Un8u5CDpGYT9kq0
l6eB5eZrpDGfveuyCzykOk7BLUWA9DkIbZWYZ4uoWiraa9GtokM5E2yElW+V
3OruvtQtAQXkmDpi0LqnX9oAK1gkQBIROeBU5sv2F1ozHaaHuyRaop2fYqcm
sBOV7zIuuGKzcVn/QSm9xg4khuuiA4quBdGNqjX4hlwQwKaE1Exwf4A828Lp
cHi7ptccJLDMdRPHWEcBR5RFNtXTKCZwzieZAEvQgYrdRHGEgJ2jJMRSw60r
lLNR5yIKiHiRdvC0XP2GtUUpfICRYWntQG7jxeuLtr5GT9FkplNZd4YbqQ8G
XoSlLdGUBbVho2va/uVI5d273El60rFJ6HnGtIIN2tjP5jHc44mKMdQVSIJ1
eV4PM2kzEtevb9K6liP2vgc9xy5VL1yXksAzIrw4Ig0lq6TOr2PVkatPIjxS
gXlYdfa60j+0mw4+hgEcixX6SeOiu00WN99B1a28kneMk8nn+pTQAoOB0/yj
32GEry2453dksi+y+hIuubMNFCyo7UQY0615TkuoiX2/Z6/W1xY0zkIZm6nE
DSWY44zIcCs302vA6k4LSeVIu7ScfjtWk8ORGY8Oo+PgaGSmwfgkPgzMWRgF
R+PZeHhqxqdHJ8OJDWHrVRmvozyQety6Hriu1HAYwpvli7V/9c4Wrtxnyb4r
/vCbngjdo5I7x1qZSQ/bwvUw/DqxzoYYDrmeYJMbSlXAhwm/3Xi0OwL0MXUl
6j/P894mn81kWPshw+adZY3azjqPVd2BaF3SS3ixyjZP9DNlVLtf+okTuX2a
FF5/jm9FqkWWdHALHn/9FD4Gvw2InRm+DZDmmXwbKK05do6VFOWGq40jLpcy
HIN1Z+H8D0xtYbsSukTHxVXtO9GXGZfTGVA1kpIDPeiSY40OUKomIqIKYtj7
cWvP5YCa4iaiGMYazXCSOLXh4XajkAX4/8SI7FUfq4l2vWb43p/NmiWVXLdt
tNpqlqnd6yC8xR7TPSVMRtPNMxdC2nOlC3s6LgoKjvoR5kkTYmzqg0bGHWcB
Yv1lM/YEAr0ZjdqtD7ygppxg1G9S9GdKGzmz7Yw6QmhYVj+R/rJelWUfaYD7
qPB1NLZC6/Z+fucyadOFMyfZGs0WhIAjXM7O99JCtezovlHdKbesSjiqi9ox
IQXwf/WlADpA2by1QqhbKzouLLkeP35Md6t7+P+OHtLH1xevnl29vXjy7JoC
hXufwdrePs2CED98MD05GZ9Fg2kwiMcnwdEsHAdnZ2dRMBsejc00Pj4dHB89
2Me9r8vGzQBr4Vobnstz4SBtBO7vl2/deSblrsy9z8qgyF7aqx4gN/ykt7t9
aYkT1uMslyWxWULcv2A66JD694Pgm0atkrD8nwyd4YWbovePVTyXDF9bIjlp
VOrPs4gilwND2hqvwxW2Pw6g0qToVVZeVJUkqz1TaXNEQ+2JUtQAjS+6n7bM
I86LrVeSg7btHuwhKD4FcLHpQjbWNX3rSRBiwjRfR4IXkNNMASidCZ4iXua3
UnxJYKxXEbkjDnSq1RHYqEsg9b+Tgda0wNG+rrG9/qQrUR2p9Sw27hCXGhDw
ND/Iixe1IwjysXYLfdmIchG74pYJ11dRion8aO7GIw3elCcZsZmJxAvhP9JF
McIO08lUDCGFMpGLt7A/p7a1q1yUUMoC2GMC31HwbQ4oxKL0YNgb9ejCq8ux
cTaExZ8HqqMeKYBwlzxaaXnNs8cRxyZtLx29AHKNwGUDRSoUcTI7PZwOj49O
ZrPhLDw6nJ6NonB4OhyfmmF0fBTNwlE0ng5nBhTiycnodAxUFY0Gg+HoODob
HJ/JnXhuh70u0kmdweUbasfjU9dqRGOUD7ZBbd65/1ejpiCxEmM2fvPx73+7
/nj9/M3Ry/Dnn67++uKXv8021dXH4B9DmP+qOry6+Okv1c3PNwxA66qKu8dT
u9SNqo6GpW/7PHzVos+Z2pNyJ/PhUejLekfCeV5bia9Yrr9DCHAKpSVUmziQ
0J9ruKcposTc2n3XH4M9rCr0tMg3LpHjT0yd0pKSm639WzZTFmE/XS+yXihn
x0Dwbdx1WHW5JFTMgSzvHaMAw1U834jVVl1OoxBngvhu3DQ54A4UArC1KTug
9cp3PLC5akfAFv3RXqPvV/4o24QlS+wG+1+3wYtZxfd6LNBUypN0un21NFE1
R+I2jah0sVrr85vUQr9OenoGq8uqsBdSxBTFY4pE8UzX4D9bJsaB96aDg4EJ
hLfRF7RUn7tlz5fDYH9FHDWD8BwncPHlSO3BqL1GvwlbK1lqMDwXhE66i+FX
NbnOg1ZoM3ArsyUpb6cA7M1n6EzOy34JumZ41HfdBJbRETsC6E434wZIAuMz
M5tGp8dmGJqz2eF4CuLYHM4GZ8dHR7GJz0hx9kcnx8PDYNH/5/Bk1Ftl/LMW
48GpiUbD6GgQxrPDYWTG0QykdxydDqeDoTnpGAqAfN729u8/Y1RmNhtFR+Z0
FJwMx6NgHB3OgulpGAaH8fHxKDqO4hMkLErGRVEH9Sl3B33Ck4oZDqjCK40G
QeST20UhfA4wqkvoY2w9k57XwaXrB3Wu3S33+wDbp8peugvg7btOJEqtCxMz
Hlld+mGPtMPoutfKd5/kv2EqOlmuX/PD+/6VS6+AZZdlaiNYulZ5hd9i5bqu
N0t7inTUYUWnKe0xplslHWqt1pl0HNrEHT45wF63YHe1z6vUJfEi4KPjix5y
tLpnHepnhE78UUKS7s5HTo0rqIIONnwhObyf8vyG6o4bkL4Fg812ovhi9xFq
Nlq3Z7UOOg9r1eV6bZsUqpPa9rTXjQhwTJu1b6aZInZ1izD/P6Q0UfoUE8En
ocKWKaI30mRKt4Qe2l+84FAuLitVTTBNRuaHspeXagw+KFtxw/r+2Rd8fOy+
2ZY1w9Hs9Gx2FgbxcWiC8eBwFJj45DAYH0+PT8PRdDw8MhPLocomWKdwOFJz
5ncQ7A592j3UGOhg5vvAIaabh0kxG8rW2XKyfrc8SFlJw2X2oKSqNPa71fKe
JC5vtcWfyQL94auhfdzj4XJ9G6jzXP8gpspms+ltDql8OCv78NV3rbcjzG4u
y3rEChwCej8K+/QVzk9DvgEyMYYMAfWTKZPQdfP5Xr6zANDvmOi9C+/k9+w7
ONoF538IOV8zfHzgPo8e9z5/ZjttxZ0JSa323dVJmq0rBnKv/VrI/kejR81b
jQDa7u1quWjMj78sK9Ft6OgLriNsplywobXkX3qgSk0S71K1hDGMJSkP8FGw
JxhVIwlAxs8gu0ukVHkk1V1e596WgPYyj7GUcuA41yi3cVFJrxLuy4Q/84BX
Iqgxub0H3az84B+wYZJNlrCRIvxxz7o/HRfa+/BSP83nOarsPWe/M+Wm1Y97
F6vVngZiJgqr4avjZi15VG9SuV9z+fwN/J62douk1tVuq4W7buMnpXSnRE1C
mW21k57dadJOzd8KvstburwtXQ5YZ1lrF1hs1dy6461JA3niW/C58Bbqn7Mh
gYfX30q+UIXtIaZrNGbobmiKPgsWHEYqxFwrqTnW3FSgBkYNgiXqdLWSajvq
ubVaUal9d6ctywCrRY7BbzwEdMabxpOjf7kLRAk0p3oVt3m4Tbj7dV2dDNT7
4ZLaoqATgTiy83MDLPROtG2Bz3fwGizDHfC5ChBv7HNhAk5L0JYdijYpm7Qk
WpvQoSayvKMQEOQT+9Yt8FjuWkXA2fkvuV9R2KVnvxmFYKQVU0C67FgZfVnh
zdI2qvW3QngTSxCZmsEE6wG9LkYAw75eTjPs6HvPZXlo/z9fxxvpF4EwlDFe
+Uf7hL4/qMvHSI07hwWDJqkBj+OrFhsennhr1bIt13tkj++xN84rMyjkQS2x
GRkWvzeZmpHCVGgLZW0fC48PxW5mohViadJ5XczhaqL57Qcl/7qVJ29dDxmM
7mb6LthsRcw85kCDJ0Xc9RcPLXX7DgGwFFaerbNQNIGIBTI438tv8UnY6Oik
Dhv5Z9EJXJ9w/f2f/lgXyafv//gTltygE/NJqedJKtksrrKXVTgVUmOrPrdV
vtLr1detLMrje1j+RxnyBZqRARbQe4z6j8OZI+zWCdq6LAx7+L+lSLesuk9T
cX7IarJatLjXm5rgsrJle6V37hJ8ask5dlmMNEXDAnAWoXFNJoS1CUsCd0vV
WxglR2rWGSkESmLKFKWdY0/IaU99uMSYvRNixIjcTzo0K6/XR3OBhhnS5oja
TqQg4gTOdeLs4HuIhMeK9VXXFQICDbiMNGEfMzWT+q6t32a8BVTXYTV4vlsL
2B8MopZm1uhqMG+n/GhabJZPy9DgshFWZKu/vH32cwtybSiGKcizJ0IzK5c1
IoMtA3OSqpZ6fuCzeURogmJ1XUo/KWDFB80oVmF9ueFASaNV1CGU07xsHqhP
g3SmlvWECr9Vx3y4dPiRmbkiEfaHv0Rp5U4Du/YGsEzslCCVf0iLNb/+s9Hy
1kpV2jGGcOiuhnc/qXEiZO4hINSXphFEoiI4dRG6TjL8sxRsWrWe3rN3rvyU
ERZ+UoXjJq+x0fz9wVVemlRq/H85fMKdZsWO5IhL5w+ifvrE9zAm/NOnPEB5
A7p+EpWqESn1RWt4gGxM6Tr2O+dGfhuV8pXy+6MPSu/nRmE597OntoF/Xt8+
rp01QHj3z3PS1VP5SVC8e2q7LiOhwE6op2EJh8X3XOnnRKjsXFqSAdD41rsY
DQQwZqToscD+2LbErzzwarswSMI7xt+WxNgbLTcT+9MZC9YmwnJQV7hLkVOY
tfS6ZN1yRbE7xg3/WKX3WwOeF+d1TfLcBGpjtetO2kLeBllxkAn74UjZiDtA
XNR1A+ASZL6IEvl9m7q6HW7r1ra2aV1eNCGRCDjZLPQ7UHyRkWJpsMO6E1Lr
FywbrW9LqW2iH40jCWGyG/1zYRZmqf+abjNg5CemwBJL/RMeSAYrv8u3+n0P
aC5O+VbYFVBinsWlWW4P1F/WKVadAm2Fixv+VannBc76DKULzqDJcwH3cM0X
bOM4ou7pdIOafwJHbkf/N8NH/wgQfQAA

-->

</rfc>

